LICENSE
MANIFEST.in
README.rst
setup.py
google/__init__.py
google/cloud/__init__.py
google/cloud/proto/__init__.py
google/cloud/proto/monitoring/__init__.py
google/cloud/proto/monitoring/v3/__init__.py
google/cloud/proto/monitoring/v3/common_pb2.py
google/cloud/proto/monitoring/v3/common_pb2_grpc.py
google/cloud/proto/monitoring/v3/group_pb2.py
google/cloud/proto/monitoring/v3/group_pb2_grpc.py
google/cloud/proto/monitoring/v3/group_service_pb2.py
google/cloud/proto/monitoring/v3/group_service_pb2_grpc.py
google/cloud/proto/monitoring/v3/metric_pb2.py
google/cloud/proto/monitoring/v3/metric_pb2_grpc.py
google/cloud/proto/monitoring/v3/metric_service_pb2.py
google/cloud/proto/monitoring/v3/metric_service_pb2_grpc.py
proto_google_cloud_monitoring_v3.egg-info/PKG-INFO
proto_google_cloud_monitoring_v3.egg-info/SOURCES.txt
proto_google_cloud_monitoring_v3.egg-info/dependency_links.txt
proto_google_cloud_monitoring_v3.egg-info/namespace_packages.txt
proto_google_cloud_monitoring_v3.egg-info/requires.txt
proto_google_cloud_monitoring_v3.egg-info/top_level.txt